githubapi4research/__init__.py
githubapi4research/commitapi4research.py
githubapi4research/commitcommentsapi4research.py
githubapi4research/githubapi4research.py
githubapi4research/issueapi4research.py
githubapi4research/issuecommentsapi4research.py
githubapi4research/pullrequestapi4research.py
githubapi4research/pullrequestcommentsapi4reseach.py
githubapi4research-0.0.2.dist-info/LICENSE
githubapi4research-0.0.2.dist-info/METADATA
githubapi4research-0.0.2.dist-info/WHEEL
githubapi4research-0.0.2.dist-info/top_level.txt
githubapi4research-0.0.2.dist-info/RECORD
