Metadata-Version: 2.1
Name: githubapi4research
Version: 0.0.2
Summary: easier to use github api for research
Home-page: https://github.com/nixianjun6/githubapi4research
Author: nixianjun6
Author-email: 18373052@buaa.edu.cn
Classifier: Programming Language :: Python :: 3
Classifier: License :: OSI Approved :: MIT License
Classifier: Operating System :: OS Independent
License-File: LICENSE
